IBP_Sampler_Package/IBP_Sampler.py
IBP_Sampler_Package/__init__.py
STA_663_IBP-0.1.dist-info/LICENSE
STA_663_IBP-0.1.dist-info/METADATA
STA_663_IBP-0.1.dist-info/WHEEL
STA_663_IBP-0.1.dist-info/top_level.txt
STA_663_IBP-0.1.dist-info/RECORD
