Metadata-Version: 2.1
Name: STA-663-IBP
Version: 0.1
Summary: STA663 - Final Project: Implementation of Indian Buffet Process
Home-page: https://github.com/peytonychen7/STA-663-Final-Project
Author: Raghav Agrawal, Yiqian (Peyton) Chen
Author-email: raghav.agrawal@duke.edu, yiqian.chen@duke.edu
License: UNKNOWN
Project-URL: Bug Tracker, https://github.com/peytonychen7/STA-663-Final-Project/issues
Platform: UNKNOWN
Classifier: Programming Language :: Python :: 3
Classifier: License :: OSI Approved :: MIT License
Classifier: Operating System :: OS Independent
Requires-Python: >=3.6
